.gitignore
CHANGES
GPL.txt
LICENSE-OPENSOURCE.txt
MANIFEST
PKG-INFO
README.txt
setup.py
src/infomedia/VERSION
src/infomedia/__init__.py
src/infomedia/collections.py
src/infomedia/options.py
src/infomedia/patterns.py
src/infomedia/hash2cfg/__init__.py
src/infomedia/hash2cfg/defines.py
src/infomedia/hash2cfg/test/__init__.py
src/infomedia/hash2cfg/test/defines.py
src/infomedia/hash2cfg/test/hash2cfg.py
src/infomedia/hash2cfg/test/simplefuncs.py
src/infomedia/test/__init__.py
src/infomedia/test/collections.py
src/infomedia/test/options.py
src/infomedia_python.egg-info/PKG-INFO
src/infomedia_python.egg-info/SOURCES.txt
src/infomedia_python.egg-info/dependency_links.txt
src/infomedia_python.egg-info/top_level.txt