Metadata-Version: 1.1
Name: infomedia-python
Version: 1.2
Summary: Infomedia Python Utility Module
Home-page: http://infomedia.it/dev
Author: Infomedia Dev Group
Author-email: dev@infomedia.it
License: GPL
Platform: UNKNOWN
Classifier: Development Status :: 4 - Beta
Classifier: Environment :: Console
Classifier: Intended Audience :: Developers
Classifier: License :: OSI Approved :: Python Software Foundation License
Classifier: Operating System :: MacOS :: MacOS X
Classifier: Operating System :: Microsoft :: Windows
Classifier: Operating System :: POSIX
Classifier: Programming Language :: Python
Classifier: Topic :: Software Development :: Libraries :: Python Modules
